qwhois/__init__.py
qwhois/whois.py
qwhois/data/public_suffix_list.dat
qwhois/data/whois_server.map
whois/__init__.py
whois/whois.py
qwhois-1.0.1.dist-info/METADATA
qwhois-1.0.1.dist-info/WHEEL
qwhois-1.0.1.dist-info/top_level.txt
qwhois-1.0.1.dist-info/RECORD
